<?xml version="1.0" encoding="UTF-8" ?>

<Include>	
    <Resources RootFolder="Global">
		<Texture Id="txrBlank" Source="blank" />
        <Font Id="Splash14Font" Source="Splash14Font" />
		<Font Id="fntSystem" Source="SystemFont" />
    </Resources>

	<Resources RootFolder="Sound">
		<SoundFile Id="sndExplosion" Source="skeletonFX_explosion"/>
		<SoundFile Id="sndBombHiss" Source="bombHiss"/>

        <SoundFile Id="sndParachute_open" Source="parachute_open"/>
        
        <SoundFile Id="sndTowerAlarm" Source="tower_alarm"/>

        <SoundFile Id="sndEnemyRatDying" Source="skeletonFX_enemy_dead_scream_1"/>
        <SoundFile Id="sndEnemyRatHit1" Source="rat_hit1_demo"/>
        <SoundFile Id="sndEnemyRatHit2" Source="rat_hit2_demo"/>

		<SoundFile Id="sndExitFlight" Source="skeletonFX_roket_start"/>
        <SoundFile Id="sndExitDoorOpen" Source="skeletonFX_door_open"/>
        <SoundFile Id="sndExitDoorClose" Source="skeletonFX_door_close"/>
	</Resources>
	
    <Resources RootFolder="Textures">
        <Texture Id="txrExplosion" Source="boom_new"/>
        <Texture Id="txrBomb" Source="bomb"/>
        <Texture Id="txr_parachute" Source="parashut_03" />

        <Texture Id="txrSmoke_1" Source="smoke_01"/>
        <Texture Id="txrSmoke_2" Source="smoke_02"/>
        <Texture Id="txrSmoke_3" Source="smoke_03"/>
        <Texture Id="txrSmoke_4" Source="smoke_04"/>

        <Texture Id="txrExitStatic" Source="refrigerator_pose_01_static"/>
        <Texture Id="txrExitReady" Source="refrigerator_pose_02_static"/>
        <Texture Id="txrExitFlight" Source="refrigerator_pose_03_flight"/>
        <Texture Id="txrExitTransform" Source="refrigerator_spr_80x111x11"/>
        <Texture Id="txrExitFlightFire" Source="exit_demo_fire_sprite_16x34x4"/>
        
        <Texture Id="txrFishBones" Source="fish_skelet_demo" />
        
        <Texture Id="txrFishTypeDefault_1" Source="fishType01" />
        <Texture Id="txrFishTypeDefault_2" Source="fishType02" />
        <Texture Id="txrFishTypeDefault_3" Source="fishType03" />
        <Texture Id="txrFishTypeDefault_4" Source="fishType04" />
        <Texture Id="txrFishTypeDefault_5" Source="fishType05" />
        <Texture Id="txrFishTypeDefault_6" Source="fishType06" />
        <Texture Id="txrFishTypeDefault_7" Source="fishType07" />


        <!-- rat 1 -->
        <Texture Id="txrEnemyRatDefaultType_1" Source="BM_Ws_pose_static" />
        <Texture Id="txrEnemyRatAttackType_1" Source="BM_Ws_1_blow_spr_80x80x6" />
        <Texture Id="txrEnemyRatDyingType_1" Source="BM_Ws_pose_static" />
        <Texture Id="txrEnemyRatWalkType_1" Source="BM_Ws_walk_spr_80x80x4" />
        <Texture Id="txrEnemyRat1_OnRest1" Source="BM_Ws_eats_spr_80x80x12x9" />
        <Texture Id="txrEnemyRat1_OnRest2" Source="BM_Ws_eats_spr_80x80x12x9" />

        <!-- rat 2 -->
        <Texture Id="txrEnemyRatDefaultType_2" Source="BM_Ms_pose_static" />
        <Texture Id="txrEnemyRatAttackType_2" Source="BM_Ms_1_blow_spr_80x80x6" />
        <Texture Id="txrEnemyRatDyingType_2" Source="BM_Ms_pose_static" />
        <Texture Id="txrEnemyRatWalkType_2" Source="BM_Ms_walk_spr_80x80x4" />
        <Texture Id="txrEnemyRat2_OnRest1" Source="BM_Ms_eats_spr_P1_80x80x12x9" />
        <Texture Id="txrEnemyRat2_OnRest2" Source="BM_Ms_juggler_spr_P1_80x80x12x9" />
        
        <!-- rat 3 -->
        <Texture Id="txrEnemyRatDefaultType_3" Source="BM_F_pose_static" />
        <Texture Id="txrEnemyRatAttackType_3" Source="BM_F_blow_spr_80x80x6" />
        <Texture Id="txrEnemyRatDyingType_3" Source="BM_F_pose_static" />
        <Texture Id="txrEnemyRatWalkType_3" Source="BM_F_walk_spr_80x80x4" />
        <Texture Id="txrEnemyRat3_OnRest1" Source="BM_F_gum_spr_80x80x12x12x5" />
        <Texture Id="txrEnemyRat3_OnRest2" Source="BM_F_gum_spr_80x80x12x12x5" />

        <!-- rat 4 -->
        <Texture Id="txrEnemyRatDefaultType_4" Source="BM_K_pose_static" />
        <Texture Id="txrEnemyRatAttackType_4" Source="BM_K_blow_spr_80x80x6" />
        <Texture Id="txrEnemyRatDyingType_4" Source="BM_K_pose_static" />
        <Texture Id="txrEnemyRatWalkType_4" Source="BM_K_walk_spr_80x80x4" />
        <Texture Id="txrEnemyRat4_OnRest1" Source="BM_K_looks_spr_80x80x12x9" />
        <Texture Id="txrEnemyRat4_OnRest2" Source="BM_K_juggler_spr_80x80x12x3" />

        <!-- rat 7 -->
        <Texture Id="txrEnemyRatDefaultType_7" Source="BM_Gb_pose_static" />
        <Texture Id="txrEnemyRatAttackType_7" Source="BM_Gb_blow_spr_80x80x6" />
        <Texture Id="txrEnemyRatDyingType_7" Source="BM_Gb_pose_static" />
        <Texture Id="txrEnemyRatWalkType_7" Source="BM_Gb_walk_spr_80x80x4" />
        <Texture Id="txrEnemyRat7_OnRest1" Source="BM_Gb_read_spr_80x80x12x12x11" />
        <Texture Id="txrEnemyRat7_OnRest2" Source="BM_Gb_smoke_spr_P3_80x80x12x12x12x9" />

        <Texture Id="txr_butter_8" Source="butter_08" />
        <Texture Id="txr_butter_7" Source="butter_07" />
        <Texture Id="txr_butter_1" Source="butter_01" />
        <Texture Id="txr_butter_6" Source="butter_06" />
        <Texture Id="txr_butter_3" Source="butter_03" />
        <Texture Id="txr_butter_4" Source="butter_04" />
        <Texture Id="txr_butter_5" Source="butter_05" />
        <Texture Id="txr_butter_2" Source="butter_02" />
        
        <Texture Id="txrBlowFlash1" Source="blow_flash_1_spr_57x56x3" />
        <Texture Id="txrBlowFlash2" Source="blow_flash_2_spr_64x64x3" />
        <Texture Id="txrBlowFlash3" Source="blow_flash_3_spr_50x54x3" />
        <Texture Id="txrBlowFlash4" Source="blow_flash_4_spr_37x35x3" />
        
    </Resources>
</Include>