<?xml version="1.0" encoding="utf-8"?>
<!-- SVG to XGAME xml converter v1.6.12 -->
<!-- source: D:\Lunohod\Levels\Lvl_1D_Enemies_v1\Lvl_1D_Enemies_v1.svg -->
<Level xmlns:xsi="http://www.w3.org/2001/XMLSchema-instance" xsi:noNamespaceSchemaLocation="file:///D:/Lunohod/Documentation/schema0.xsd" Name="Lvl_1D_Enemies_v1" Bounds="0, 0, 480, 320">
    <Include File="ClassOil.xml" />
    <Include File="ClassOilSpot.xml" />
    <Include File="ClassBarrel.xml" />
    <Include File="ClassEnemyRat4.xml" />
    <Include File="ClassEnemyRat2.xml" />
    <Include File="ClassWoodenBox.xml" />
    <Include File="ClassFood.xml" />
    <Include File="ClassTower.xml" />
    <Include File="ClassExit.xml" />
    <Include File="ClassHero.xml" />
    <Resources RootFolder="Textures">
        <Texture Id="txr_under_land_level_BG" Source="under_land_level_BG" />
        <Texture Id="txr_laz_vert_01" Source="laz_vert_01" />
        <Texture Id="txr_laz_vert_02" Source="laz_vert_02" />
        <Texture Id="txr_laz_bckgrnd_01" Source="laz_bckgrnd_01" />
        <Texture Id="txr_laz_hor_01" Source="laz_hor_01" />
        <Texture Id="txr_laz_turn_02" Source="laz_turn_02" />
        <Texture Id="txr_web_02" Source="web_02" />
        <Texture Id="txr_stone_brown_03" Source="stone_brown_03" />
        <Texture Id="txr_stone_brown_01" Source="stone_brown_01" />
        <Texture Id="txr_stone_brown_02" Source="stone_brown_02" />
        <Texture Id="txr_bones_01" Source="bones_01" />
        <Texture Id="txr_bones_09" Source="bones_09" />
        <Texture Id="txr_bones_02" Source="bones_02" />
        <Texture Id="txr_bones_03" Source="bones_03" />
        <Texture Id="txr_bones_04" Source="bones_04" />
        <Texture Id="txr_bones_07" Source="bones_07" />
        <Texture Id="txr_metal_02" Source="metal_02" />
        <Texture Id="txr_metal_01" Source="metal_01" />
        <Texture Id="txr_barrel" Source="barrel" />
        <Texture Id="txr_butter_05" Source="butter_05" />
        <Texture Id="txr_butter_03" Source="butter_03" />
        <Texture Id="txr_butter_04" Source="butter_04" />
        <Texture Id="txr_box_old_1" Source="box_old_1" />
    </Resources>
    <Layer Id="blocks" BackColor="#FFFFFFFF">
        <Block Id="blk1" Bounds="0, -30, 480, 50" Edges="Stick" TraceId="image4815"/>
        <Block Id="blk2" Bounds="0, 290, 480, 72" Edges="Stick" TraceId="image4822"/>
        <Block Id="blk3" Bounds="262, 50, 118, 90" Edges="Stick" TraceId="image3217"/>
        <Block Id="blk4" Bounds="262, 170, 118, 90" Edges="Stick" TraceId="image3222"/>
        <Block Id="blk5" Bounds="102, 20, 120, 120" Edges="Stick" TraceId="image3224"/>
        <Block Id="blk6" Bounds="-2, 170, 224, 128" Edges="Stick" TraceId="image3226"/>
        <Block Id="blk7" Bounds="420, 0, 80, 357" Edges="Stick" TraceId="image3228"/>
        <Block Id="blk8" Bounds="-18, 0, 80, 357" Edges="Stick" TraceId="image3230"/>
    </Layer>
    <Layer Id="background" BackColor="#FFFFFFFF">
        <Image Id="dfltMask1" TextureId="txr_under_land_level_BG" Bounds="0, 0, 480, 320" TraceId="image3107"/>
    </Layer>
    <Layer Id="Laz New" BackColor="#FFFFFFFF">
        <Image Id="dfltMask2" TextureId="txr_laz_vert_01" Bounds="57, 80, 49, 30" TraceId="image3135"/>
        <Image Id="dfltMask3" TextureId="txr_laz_vert_02" Bounds="57, 50, 49, 30" TraceId="image3146-1"/>
        <Image Id="dfltMask4" TextureId="txr_laz_vert_01" Bounds="57, 110, 49, 30" TraceId="image3149"/>
        <Image Id="dfltMask5" TextureId="txr_laz_vert_01" Bounds="217, 50, 49, 30" TraceId="image3151"/>
        <Image Id="dfltMask6" TextureId="txr_laz_vert_01" Bounds="217, 80, 49, 30" TraceId="image3153"/>
        <Image Id="dfltMask7" TextureId="txr_laz_vert_02" Bounds="217, 110, 49, 30" TraceId="image3155"/>
        <Image Id="dfltMask8" TextureId="txr_laz_bckgrnd_01" Bounds="217, 140, 49, 30" Stretch="true" TraceId="image3157"/>
        <Image Id="dfltMask9" TextureId="txr_laz_vert_01" Bounds="217, 170, 49, 30" TraceId="image3159"/>
        <Image Id="dfltMask10" TextureId="txr_laz_vert_02" Bounds="217, 200, 49, 30" TraceId="image3161"/>
        <Image Id="dfltMask11" TextureId="txr_laz_vert_01" Bounds="217, 230, 49, 30" TraceId="image3163"/>
        <Image Id="dfltMask12" TextureId="txr_laz_vert_01" Bounds="375, 50, 49, 30" TraceId="image3171"/>
        <Image Id="dfltMask13" TextureId="txr_laz_vert_02" Bounds="375, 80, 49, 30" TraceId="image3174"/>
        <Image Id="dfltMask14" TextureId="txr_laz_vert_01" Bounds="375, 110, 49, 30" TraceId="image3176"/>
        <Image Id="dfltMask15" TextureId="txr_laz_vert_01" Bounds="375, 140, 49, 30" TraceId="image3178"/>
        <Image Id="dfltMask16" TextureId="txr_laz_vert_01" Bounds="375, 170, 49, 30" TraceId="image3181"/>
        <Image Id="dfltMask17" TextureId="txr_laz_vert_01" Bounds="375, 200, 49, 30" TraceId="image3185"/>
        <Image Id="dfltMask18" TextureId="txr_laz_vert_02" Bounds="375, 230, 49, 30" TraceId="image3187"/>
        <Image Id="dfltMask19" TextureId="txr_laz_hor_01" Bounds="262, 17, 40, 36" TraceId="image3214"/>
        <Image Id="dfltMask20" TextureId="txr_laz_hor_01" Bounds="302, 17, 40, 36" TraceId="image3216"/>
        <Image Id="dfltMask21" TextureId="txr_laz_hor_01" Bounds="342, 17, 40, 36" TraceId="image3218"/>
        <Image Id="dfltMask22" TextureId="txr_laz_hor_01" Bounds="262, 257, 40, 36" TraceId="image3231"/>
        <Image Id="dfltMask23" TextureId="txr_laz_hor_01" Bounds="302, 257, 40, 36" TraceId="image3233"/>
        <Image Id="dfltMask24" TextureId="txr_laz_hor_01" Bounds="342, 257, 40, 36" TraceId="image3235"/>
        <Image Id="dfltMask25" TextureId="txr_laz_hor_01" Bounds="102, 137, 40, 36" TraceId="image3239"/>
        <Image Id="dfltMask26" TextureId="txr_laz_hor_01" Bounds="142, 137, 40, 36" TraceId="image3241"/>
        <Image Id="dfltMask27" TextureId="txr_laz_hor_01" Bounds="182, 137, 40, 36" TraceId="image3243"/>
        <Image Id="dfltMask28" TextureId="txr_laz_hor_01" Bounds="262, 137, 40, 36" TraceId="image3247"/>
        <Image Id="dfltMask29" TextureId="txr_laz_hor_01" Bounds="302, 137, 40, 36" TraceId="image3249"/>
        <Image Id="dfltMask30" TextureId="txr_laz_hor_01" Bounds="342, 137, 40, 36" TraceId="image3251"/>
        <Image Id="dfltMask31" TextureId="txr_laz_turn_02" Bounds="380, 16, 44, 34" TraceId="image3263"/>
        <Image Id="dfltMask32" TextureId="txr_laz_turn_02" Bounds="102, 174, 44, 34" Rotation="180" Stretch="true" TraceId="image3266"/>
        <Image Id="dfltMask33" TextureId="txr_laz_turn_02" Bounds="262, 294, 44, 34" Rotation="180" Stretch="true" TraceId="image3272"/>
        <Image Id="dfltMask34" TextureId="txr_laz_turn_02" Bounds="218, 16, 44, 34" FlipEffects="Horizontally" TraceId="image3764"/>
        <Image Id="dfltMask35" TextureId="txr_laz_turn_02" Bounds="424, 294, 44, 34" Rotation="180" Stretch="true" FlipEffects="Horizontally" TraceId="image3766"/>
    </Layer>
    <Layer Id="secondbckg" BackColor="#FFFFFFFF">
        <Image Id="dfltMask36" TextureId="txr_web_02" Bounds="221, 17, 27, 29" Stretch="true" TraceId="image3566"/>
        <Image Id="dfltMask37" TextureId="txr_stone_brown_03" Bounds="9, 57, 15, 16" TraceId="image3624"/>
        <Image Id="dfltMask38" TextureId="txr_stone_brown_03" Bounds="-7, 109, 15, 16" TraceId="image3626"/>
        <Image Id="dfltMask39" TextureId="txr_stone_brown_03" Bounds="23, 182, 15, 16" TraceId="image3628"/>
        <Image Id="dfltMask40" TextureId="txr_stone_brown_03" Bounds="444, 58, 15, 16" TraceId="image3630"/>
        <Image Id="dfltMask41" TextureId="txr_stone_brown_03" Bounds="448, 185, 15, 16" TraceId="image3599"/>
        <Image Id="dfltMask42" TextureId="txr_stone_brown_01" Bounds="171, 217, 15, 12" TraceId="image3632"/>
        <Image Id="dfltMask43" TextureId="txr_stone_brown_01" Bounds="456, 174, 15, 12" TraceId="image3634"/>
        <Image Id="dfltMask44" TextureId="txr_stone_brown_01" Bounds="460, 255, 15, 12" TraceId="image3636"/>
        <Image Id="dfltMask45" TextureId="txr_stone_brown_01" Bounds="456, 290, 15, 12" TraceId="image3610"/>
        <Image Id="dfltMask46" TextureId="txr_stone_brown_02" Bounds="161, 281, 11, 10" TraceId="image3756"/>
        <Image Id="dfltMask47" TextureId="txr_stone_brown_02" Bounds="333, 90, 11, 10" TraceId="image3758"/>
        <Image Id="dfltMask48" TextureId="txr_stone_brown_02" Bounds="357, 106, 11, 10" TraceId="image3760"/>
        <Image Id="dfltMask49" TextureId="txr_stone_brown_02" Bounds="286, 201, 11, 10" TraceId="image3762"/>
        <Image Id="dfltMask50" TextureId="txr_stone_brown_02" Bounds="173, 306, 11, 10" TraceId="image3640"/>
        <Image Id="dfltMask51" TextureId="txr_stone_brown_02" Bounds="128, 20, 11, 10" TraceId="image3642"/>
        <Image Id="dfltMask52" TextureId="txr_bones_01" Bounds="69, 222, 35, 31" TraceId="image3663"/>
        <Image Id="dfltMask53" TextureId="txr_bones_09" Bounds="112, 223, 19, 23" TraceId="image3674"/>
        <Image Id="dfltMask54" TextureId="txr_bones_02" Bounds="66, 209, 15, 12" TraceId="image3685"/>
        <Image Id="dfltMask55" TextureId="txr_bones_03" Bounds="99, 258, 15, 18" TraceId="image3696"/>
        <Image Id="dfltMask56" TextureId="txr_bones_04" Bounds="119, 247, 15, 19" TraceId="image3707"/>
        <Image Id="dfltMask57" TextureId="txr_bones_07" Bounds="342, 170, 21, 13" TraceId="image3718"/>
        <Image Id="dfltMask58" TextureId="txr_metal_02" Bounds="130, -5, 28, 23" TraceId="image3729"/>
        <Image Id="dfltMask59" TextureId="txr_metal_01" Bounds="214, 1, 35, 26" Rotation="135" TraceId="image3740"/>
    </Layer>
    <Layer Id="oil 2" BackColor="#FFFFFFFF">
        <Group Id="grpOil1" Enabled="false">
            <Group Id="grpOilArea1" Class="clsOil" Bounds="175, 140, 90, 28" TraceId="image3162"/>
            <Image Id="img60" Class="clsOilSpot" ClassParams="@appearanceTime=1,@txrNum=8" Bounds="178, 142, 50, 25" TraceId="image3293-9" />
            <Image Id="img61" Class="clsOilSpot" ClassParams="@appearanceTime=2,@txrNum=7" Bounds="165, 141, 34, 19" TraceId="image3350" />
            <Image Id="img62" Class="clsOilSpot" ClassParams="@appearanceTime=3,@txrNum=8" Bounds="213, 149, 47, 22" TraceId="image3361" />
            <Image Id="img63" Class="clsOilSpot" ClassParams="@appearanceTime=4,@txrNum=3" Bounds="187, 143, 33, 24" TraceId="image3170" />
            <Image Id="img64" Class="clsOilSpot" ClassParams="@appearanceTime=5,@txrNum=4" Bounds="205, 144, 33, 19" TraceId="image3181-1" />
            <Image Id="img65" Class="clsOilSpot" ClassParams="@appearanceTime=6,@txrNum=2" Bounds="169, 147, 30, 22" TraceId="image3192-7" />
            <Image Id="img66" Class="clsOilSpot" ClassParams="@appearanceTime=7,@txrNum=4" Bounds="231, 141, 32, 19" TraceId="image3203" />
            <Image Id="img67" Class="clsOilSpot" ClassParams="@appearanceTime=8,@txrNum=2" Bounds="235, 153, 27, 20" TraceId="image3315" />
        </Group>
        <Block Id="blkBarrel1" Class="clsBarrel" Bounds="194, 138, 28, 32" Edges="Stick" TraceId="image3180">
            <Image TextureId="txr_barrel" />
            <BoolTrigger Condition="blkBarrel1:Destroyed" EnterAction="grpOil1.Enable()" />
        </Block>
    </Layer>
    <Layer Id="oil" BackColor="#FFFFFFFF">
        <Group Id="grpOil2" Enabled="false">
            <Group Id="grpOilArea2" Class="clsOil" Bounds="223, 94, 39, 82" TraceId="image3085-1"/>
            <Image Id="img68" Class="clsOilSpot" ClassParams="@appearanceTime=1,@txrNum=6" Bounds="224, 99, 37, 43" TraceId="image3304-4" />
            <Image Id="img69" Class="clsOilSpot" ClassParams="@appearanceTime=2,@txrNum=8" Bounds="224, 132, 36, 17" TraceId="image3225" />
            <Image Id="img70" Class="clsOilSpot" ClassParams="@appearanceTime=3,@txrNum=7" Bounds="226, 89, 34, 19" TraceId="image3236" />
            <Image Id="img71" Class="clsOilSpot" ClassParams="@appearanceTime=4,@txrNum=3" Bounds="224, 103, 36, 37" TraceId="image3258" />
            <Image Id="img72" Class="clsOilSpot" ClassParams="@appearanceTime=5,@txrNum=5" Bounds="219, 129, 37, 51" TraceId="image3269" />
            <Image Id="img73" Class="clsOilSpot" ClassParams="@appearanceTime=6,@txrNum=4" Bounds="238, 150, 28, 19" TraceId="image3280" />
        </Group>
        <Block Id="blkBarrel2" Class="clsBarrel" Bounds="227, 108, 28, 32" Edges="Stick" TraceId="image3103">
            <Image TextureId="txr_barrel" />
            <BoolTrigger Condition="blkBarrel2:Destroyed" EnterAction="grpOil2.Enable()" />
        </Block>
    </Layer>
    <Layer Id="oil 3" BackColor="#FFFFFFFF">
        <Group Id="grpOilArea3" Class="clsOil" Bounds="382, 105, 35, 81" TraceId="image3230-7"/>
        <Image Id="dfltMask74" TextureId="txr_butter_05" Bounds="382, 110, 32, 40" TraceId="image3282"/>
        <Image Id="dfltMask75" TextureId="txr_butter_05" Bounds="386, 145, 32, 40" TraceId="image3307"/>
        <Image Id="dfltMask76" TextureId="txr_butter_03" Bounds="372, 140, 33, 30" TraceId="image3293"/>
        <Image Id="dfltMask77" TextureId="txr_butter_04" Bounds="390, 131, 28, 19" TraceId="image3304"/>
    </Layer>
    <Layer Id="action" BackColor="#FFFFFFFF">
        <Enemy Id="enm1" Class="clsEnemyRat4" Bounds="234, 53, 22, 23" TraceId="image3129"/>
        <Enemy Id="enm2" Class="clsEnemyRat2" Bounds="351, 24, 22, 23" TraceId="image3240"/>
        <Block Id="blk9" Class="clsWoodenBox" Bounds="385, 22, 30, 30" Edges="Stick" TraceId="image3296">
            <Image TextureId="txr_box_old_1" />
        </Block>
        <Food Id="fd1" Class="clsFood" ClassParams="@fishType=4" Bounds="388, 111, 28, 22" TraceId="image3487"/>
        <Food Id="fd2" Class="clsFood" ClassParams="@fishType=2" Bounds="343, 145, 28, 19" TraceId="image3498"/>
        <Food Id="fd3" Class="clsFood" ClassParams="@fishType=3" Bounds="227, 239, 31, 20" TraceId="image3512"/>
        <Food Id="fd4" Class="clsFood" ClassParams="@fishType=3" Bounds="384, 238, 31, 20" TraceId="image3509"/>
        <Food Id="fd5" Class="clsFood" ClassParams="@fishType=6" Bounds="65, 73, 22, 27" TraceId="image3522"/>
        <Food Id="fd6" Class="clsFood" ClassParams="@fishType=2" Bounds="74, 98, 28, 19" TraceId="image3533"/>
    </Layer>
    <Layer Id="actionTHE" BackColor="#FFFFFFFF">
        <Tower Id="tower" Bounds="0, 0, 30, 30" Class="clsTower" TraceId="image3038"/>
        <Group Id="exit" Class="clsExit" Bounds="62, 11, 37, 54" TraceId="image3049" />
        <Hero Id="hero" Class="clsHero" Bounds="225, 143, 33, 24" TraceId="image3606"/>
    </Layer>
    <Include File="ClassExplosion.xml" />
    <Include File="Dashboard.xml" />
</Level>
<!-- Food=6 Enemy=2 Block=9 DesignImage=77 Animation=0 Teleport Animations=0 FoodPack=0 Oil Barrel=3 dealy sec=0 -->
<!-- -->
<!-- Food Points = 500 -->
<!-- 1% = 5; 45% = 225; 90% = 450 -->
<!-- minPointsFood = 70 (14%) -->
<!-- -->
<!-- Enemy Points = 100 -->
<!-- 1% = 1; 45% = 45; 90% = 90 -->
<!-- minPointsEnemy = 50 (50%) -->
<!-- -->
<!-- Food + Enemy Points = 600 -->
<!-- 1% = 6; 45% = 270; 90% = 540 -->
<!-- minPointsFood = 70 (11.7%) -->
<!-- minPointsEnemy = 50 (8.3%) -->
